LICENSE
MANIFEST.in
README.rst
requirements.txt
setup.cfg
setup.py
test-requirements.txt
ksql/__init__.py
ksql/api.py
ksql/builder.py
ksql/client.py
ksql/errors.py
ksql/upload.py
ksql/utils.py
pykSQL.egg-info/PKG-INFO
pykSQL.egg-info/SOURCES.txt
pykSQL.egg-info/dependency_links.txt
pykSQL.egg-info/not-zip-safe
pykSQL.egg-info/requires.txt
pykSQL.egg-info/top_level.txt