Metadata-Version: 2.1
Name: pykSQL
Version: 0.11.0
Summary: A Python wrapper for the KSQL REST API
Home-page: https://github.com/bryanyang0528/ksql-python
Author: Bryan Yang / Dogukan Celik
Author-email: dogukan@btslabs.ai
License: MIT License
Platform: any
Classifier: Development Status :: 5 - Production/Stable
Classifier: Intended Audience :: Developers
Classifier: Natural Language :: English
Classifier: License :: OSI Approved :: MIT License
Classifier: Programming Language :: Python
Classifier: Programming Language :: Python :: 3.5
Classifier: Programming Language :: Python :: 3.6
Classifier: Programming Language :: Python :: 3.7
Classifier: Programming Language :: Python :: 3.10
Classifier: Topic :: Software Development :: Libraries :: Python Modules
Provides-Extra: dev
License-File: LICENSE
